LICENSE
README.md
example.py
example2.py
mayhemmonkey.py
pyproject.toml
setup.cfg
mayhemmonkey-2025.2.20.post9.data/data/bin/LICENSE
mayhemmonkey-2025.2.20.post9.data/data/bin/mayhemmonkey.py
mayhemmonkey.egg-info/PKG-INFO
mayhemmonkey.egg-info/SOURCES.txt
mayhemmonkey.egg-info/dependency_links.txt
mayhemmonkey.egg-info/top_level.txt
mayhemmonkey-2025.2.20.post9.dist-info/LICENSE
mayhemmonkey-2025.2.20.post9.dist-info/METADATA
mayhemmonkey-2025.2.20.post9.dist-info/WHEEL
mayhemmonkey-2025.2.20.post9.dist-info/top_level.txt
mayhemmonkey-2025.2.20.post9.dist-info/RECORD
